testbench/definitionsDatcontroller.v
`timescale 1ns / 1ps
`ifndef DEFINTIONS_V
`define DEFINTIONS_V
	
`define HALF_PERIOD 20
`define RESET_FIRE_TIME 100
`define RESET_DEACTIVATE_TIME 250
`define NEW_DATA_REQUEST_TIME 1000
`define WRITE_READ_TIME 1000
`define WRITE_READ 1'b1
`define SERIAL_READY_TIME 1300
`define FIFOOKAY_TIME 1400
`define COMPLETE_TIME 2000
`define ACK_IN_TIME 2100

`endif

testbench/generator_datcontroller.v
module generatorDatcontroller(
// inputs from host
output wire clock,
output wire reset,
output wire writeRead,
output wire newDat,
//inputs from physical layer
output wire serial_ready,
output wire complete,
output wire ack_in,
//inputs from fifoController
output wire fifo_okay)
;

clock_gen clk1(clock);
reset_gen r1(reset);
newDat_gen nDG(newDat);
serialReady_gen sRg(serial_ready);
complete_gen  cg(complete);
fifo_okay_gen fog(fifo_okay);
ack_in_gen aig(ack_in);
writeRead_gen wRg(writeRead);



endmodule
module clock_gen(output clock);
reg clock;
initial
	begin
		clock=1'b0;
	end
always
		begin
		#`HALF_PERIOD;
		clock=1'b1;
		#`HALF_PERIOD;
		clock=1'b0;
		end
endmodule

module reset_gen(output reset);
reg reset;
initial
	begin
	reset=1'b0;
	#`RESET_FIRE_TIME
	reset=1'b1;
	#`RESET_DEACTIVATE_TIME
	reset=1'b0;
	end
endmodule

module newDat_gen(output newDat);
reg newDat;
initial
	begin
		#`NEW_DATA_REQUEST_TIME;
		newDat=1;
	end

endmodule

module writeRead_gen(output writeRead);
reg writeRead;
initial
	begin
		#`WRITE_READ_TIME;
		writeRead=`WRITE_READ;
	end
endmodule

module serialReady_gen(output serialReady);
reg serialReady;
initial
	begin
		serialReady=1'b0;
		#`SERIAL_READY_TIME;
		serialReady=1'b1;
	end
endmodule

module complete_gen(output complete);
reg complete;
initial
	begin
		complete=1'b0;
		#`COMPLETE_TIME;
		complete=1'b1;
	end
endmodule

module ack_in_gen(output ack_in);
reg ack_in;
initial
	begin
		ack_in=1'b0;
		#`ACK_IN_TIME;
		ack_in=1'b1;
	end
endmodule

module fifo_okay_gen(output fifo_okay);
reg fifo_okay;
initial
	begin
		fifo_okay=1'b0;
		#`FIFOOKAY_TIME;
		fifo_okay=1'b1;
	end
endmodule

code/dat_controller.v
module dat_controller(

// inputs from host
input wire clock,
input wire reset,
input wire writeRead,
input wire newDat,
//inputs from physical layer
input wire serial_ready,
input wire complete,
input wire ack_in,
//inputs from fifoController
input wire fifo_okay,
//outputs to host
output reg busy,
output reg write_Data,
output reg read_Data,
output reg transfer_complete,
//outputs to physical layer
output reg strobe_out,
output reg ack_out
);

// registers
parameter SIZE = 3;
reg setup_done;
reg [SIZE-1:0] state;
reg [SIZE-1:0] next_state;
parameter RESET= 3'd0; 
parameter IDLE   = 3'd1;
parameter WRITE_COMMAND   =  3'd2;
parameter READ_COMMAND =  3'd3;
parameter CHECK_FIFO= 3'd4; 
parameter TRANSMIT   = 3'd5;
parameter ACK   =  3'd6;








// registers


always @ ( state  or serial_ready or newDat or ack_in or fifo_okay )
begin 
 case(state)
 RESET:
		begin
			next_state=IDLE;
		end
 IDLE:   begin
      if (newDat)
			begin
				if(writeRead)
					next_state=WRITE_COMMAND;
				if(~writeRead)	
					next_state=READ_COMMAND;		
			end		
		else
			begin
          next_state = IDLE;
          end
      
		end       
WRITE_COMMAND:begin
    if (serial_ready)             
       next_state = CHECK_FIFO;  
     else   
       next_state = WRITE_COMMAND;
   end  
READ_COMMAND:    begin
       if (serial_ready) begin
          next_state = CHECK_FIFO;
      end     
      else begin
         next_state = READ_COMMAND;
      end
      end
CHECK_FIFO:    begin
       if (fifo_okay) begin
          next_state = TRANSMIT;
      end     
      else begin
         next_state = CHECK_FIFO;
      end
      end
TRANSMIT:    begin
       if (complete) begin
          next_state = ACK;
      end     
      else begin
         next_state = TRANSMIT;
      end
      end
ACK:    begin
       if (ack_in) begin
          next_state =IDLE;
      end     
      else begin
         next_state =ACK;
      end         
		end
    
   
  
 default : next_state  = IDLE;
 
 endcase 
    
end





always @(posedge clock )
	begin
		case(state)
			RESET:
				begin
					busy=1'b0;
					write_Data=1'b0;
					read_Data=1'b0;
					strobe_out=1'b0;
					ack_out=1'b0;
				end
			IDLE:
				begin
					busy=1'b0;
					write_Data=1'b0;
					read_Data=1'b0;
					strobe_out=1'b0;
					ack_out=1'b0;
				end
			WRITE_COMMAND:
				begin
					busy=1'b1;
					write_Data=1'b1;
					read_Data=1'b0;
					strobe_out=1'b1;
					ack_out=1'b0;
				end
			READ_COMMAND:
				begin
					busy=1;
					write_Data=1'b0;
					read_Data=1'b1;
					strobe_out=1'b1;
					ack_out=1'b0;
				end
			CHECK_FIFO:
				begin
					busy=0;
					write_Data=write_Data;
					read_Data=read_Data;
					strobe_out=1'b0;
					ack_out=1'b0;
				end
			TRANSMIT:
				begin
					busy=1'b1;
					write_Data=write_Data;
					read_Data=read_Data;
					strobe_out=1'b1;
					ack_out=1'b0;
				end
			ACK:
				begin
					busy=1'b1;
					write_Data=1'b0;
					read_Data=1'b0;
					strobe_out=1'b0;
					ack_out=1'b1;
					transfer_complete=1'b1;
				end
		
				
		default:
		
		
		busy=0;
		endcase
end	




always @ (posedge clock  )
	begin 
		if (reset) 
			begin
				state <=  RESET;
			end 
		else 
			begin
				state <=  next_state;
		end
	end

endmodule

testbench/dat_controller_tb.v
`include "definitionsDatcontroller.v"
`include "../code/dat_controller.v"
`include "generator_datcontroller.v"
module TestBench;


wire Clock;
wire Reset;
wire writeRead;
wire newDat;
wire serial_ready;
wire complete;
wire ack_in;
wire fifo_okay;
wire busy;
wire write_Data;
wire read_Data;
wire transfer_complete;
wire strobe_out;
wire ack_out;

dat_controller dat_controller_1(
.clock(Clock),
.reset(Reset),
.writeRead(writeRead),
.newDat(newDat),
.serial_ready(serial_ready),
.complete(complete),
.ack_in(ack_in),
.fifo_okay(fifo_okay),
.busy(busy),
.write_Data(write_Data),
.read_Data(read_Data),
.transfer_complete(transfer_complete),
.strobe_out(strobe_out),
.ack_out(ack_out)

);

generatorDatcontroller genDat(
.clock(Clock),
.reset(Reset),
.writeRead(writeRead),
.newDat(newDat),
.serial_ready(serial_ready),
.complete(complete),
.ack_in(ack_in),
.fifo_okay(fifo_okay)
);
	
	initial begin
	
		$dumpfile("signalsDatController.vcd");
		$dumpvars;	
		#2500
		$display("test finished");
		$finish;
	end

endmodule

testbench/signalsDatController.vcd
$date
	Sun May 15 18:42:26 2016
$end
$version
	Icarus Verilog
$end
$timescale
	1ps
$end
$scope module TestBench $end
$var wire 1 ! Clock $end
$var wire 1 " Reset $end
$var wire 1 # ack_in $end
$var wire 1 $ ack_out $end
$var wire 1 % busy $end
$var wire 1 & complete $end
$var wire 1 ' fifo_okay $end
$var wire 1 ( newDat $end
$var wire 1 ) read_Data $end
$var wire 1 * serial_ready $end
$var wire 1 + strobe_out $end
$var wire 1 , transfer_complete $end
$var wire 1 - writeRead $end
$var wire 1 . write_Data $end
$scope module dat_controller_1 $end
$var wire 1 # ack_in $end
$var wire 1 ! clock $end
$var wire 1 & complete $end
$var wire 1 ' fifo_okay $end
$var wire 1 ( newDat $end
$var wire 1 " reset $end
$var wire 1 * serial_ready $end
$var wire 1 - writeRead $end
$var reg 1 / ack_out $end
$var reg 1 0 busy $end
$var reg 3 1 next_state [2:0] $end
$var reg 1 2 read_Data $end
$var reg 3 3 state [2:0] $end
$var reg 1 4 strobe_out $end
$var reg 1 5 transfer_complete $end
$var reg 1 6 write_Data $end
$upscope $end
$scope module genDat $end
$var wire 1 # ack_in $end
$var wire 1 ! clock $end
$var wire 1 & complete $end
$var wire 1 ' fifo_okay $end
$var wire 1 ( newDat $end
$var wire 1 " reset $end
$var wire 1 * serial_ready $end
$var wire 1 - writeRead $end
$scope module clk1 $end
$var reg 1 7 clock $end
$upscope $end
$scope module r1 $end
$var reg 1 8 reset $end
$upscope $end
$scope module nDG $end
$var reg 1 9 newDat $end
$upscope $end
$scope module sRg $end
$var reg 1 : serialReady $end
$upscope $end
$scope module cg $end
$var reg 1 ; complete $end
$upscope $end
$scope module fog $end
$var reg 1 < fifo_okay $end
$upscope $end
$scope module aig $end
$var reg 1 = ack_in $end
$upscope $end
$scope module wRg $end
$var reg 1 > writeRead $end
$upscope $end
$upscope $end
$upscope $end
$enddefinitions $end
#0
$dumpvars
x>
0=
0<
0;
0:
x9
08
07
x6
x5
x4
bx 3
x2
b0 1
00
x/
x.
x-
x,
x+
0*
x)
x(
0'
0&
0%
x$
0#
0"
0!
$end
#20000
05
0,
0/
0$
04
0+
02
0)
06
0.
b1 1
b0 3
17
1!
#40000
07
0!
#60000
b1 3
17
1!
#80000
07
0!
#100000
b0 3
17
1!
18
1"
#120000
07
0!
#140000
17
1!
#160000
07
0!
#180000
17
1!
#200000
07
0!
#220000
17
1!
#240000
07
0!
#260000
17
1!
#280000
07
0!
#300000
17
1!
#320000
07
0!
#340000
17
1!
#350000
08
0"
#360000
07
0!
#380000
b1 3
17
1!
#400000
07
0!
#420000
17
1!
#440000
07
0!
#460000
17
1!
#480000
07
0!
#500000
17
1!
#520000
07
0!
#540000
17
1!
#560000
07
0!
#580000
17
1!
#600000
07
0!
#620000
17
1!
#640000
07
0!
#660000
17
1!
#680000
07
0!
#700000
17
1!
#720000
07
0!
#740000
17
1!
#760000
07
0!
#780000
17
1!
#800000
07
0!
#820000
17
1!
#840000
07
0!
#860000
17
1!
#880000
07
0!
#900000
17
1!
#920000
07
0!
#940000
17
1!
#960000
07
0!
#980000
17
1!
#1000000
b10 1
07
0!
1>
1-
19
1(
#1020000
14
1+
16
1.
10
1%
b10 3
17
1!
#1040000
07
0!
#1060000
17
1!
#1080000
07
0!
#1100000
17
1!
#1120000
07
0!
#1140000
17
1!
#1160000
07
0!
#1180000
17
1!
#1200000
07
0!
#1220000
17
1!
#1240000
07
0!
#1260000
17
1!
#1280000
07
0!
#1300000
04
0+
b100 3
b100 1
17
1!
1:
1*
#1320000
07
0!
#1340000
17
1!
#1360000
07
0!
#1380000
17
1!
#1400000
b101 1
07
0!
1<
1'
#1420000
b101 3
17
1!
#1440000
07
0!
#1460000
17
1!
#1480000
07
0!
#1500000
17
1!
#1520000
07
0!
#1540000
17
1!
#1560000
07
0!
#1580000
17
1!
#1600000
07
0!
#1620000
17
1!
#1640000
07
0!
#1660000
17
1!
#1680000
07
0!
#1700000
17
1!
#1720000
07
0!
#1740000
17
1!
#1760000
07
0!
#1780000
17
1!
#1800000
07
0!
#1820000
17
1!
#1840000
07
0!
#1860000
17
1!
#1880000
07
0!
#1900000
17
1!
#1920000
07
0!
#1940000
17
1!
#1960000
07
0!
#1980000
17
1!
#2000000
b110 1
15
1,
07
0!
1;
1&
#2020000
1/
1$
06
0.
b110 3
17
1!
#2040000
07
0!
#2060000
17
1!
#2080000
07
0!
#2100000
05
0,
0/
0$
00
0%
b1 3
b10 1
17
1!
1=
1#
#2120000
07
0!
#2140000
14
1+
16
1.
10
1%
b100 1
b10 3
17
1!
#2160000
07
0!
#2180000
04
0+
b101 1
b100 3
17
1!
#2200000
07
0!
#2220000
15
1,
b110 1
b101 3
17
1!
#2240000
07
0!
#2260000
1/
1$
06
0.
b1 1
b110 3
17
1!
#2280000
07
0!
#2300000
05
0,
0/
0$
00
0%
b10 1
b1 3
17
1!
#2320000
07
0!
#2340000
14
1+
16
1.
10
1%
b100 1
b10 3
17
1!
#2360000
07
0!
#2380000
04
0+
b101 1
b100 3
17
1!
#2400000
07
0!
#2420000
15
1,
b110 1
b101 3
17
1!
#2440000
07
0!
#2460000
1/
1$
06
0.
b1 1
b110 3
17
1!
#2480000
07
0!
#2500000
05
0,
0/
0$
00
0%
b10 1
b1 3
17
1!
